{
  "en-US": [
  {
    "ResourceKey": "ColumnID",
    "Value": "ID"
  },
  {
    "ResourceKey": "Global_SentDate",
    "Value": "Sent date"
  },
  {
    "ResourceKey": "SendTo",
    "Value": "Send To"
  },
  {
    "ResourceKey": "ClientFilter_Platform",
    "Value": "Platform"
  },
  {
    "ResourceKey": "Channel",
    "Value": "Channel"
  }, 
      {
    "ResourceKey": "Global_Status",
    "Value": "Status"
  },
  {
    "ResourceKey": "Global_Type",
    "Value": "Type"
  },
  {
    "ResourceKey": "Global_Category",
    "Value": "Category"
  }
  ],
  "es-419": [
      {
    "ResourceKey": "ColumnID",
    "Value": "ID"
  },
  {
    "ResourceKey": "Global_SentDate",
    "Value": "Fecha enviada"
  },
    
  ],
  "fr-FR": [
      {
    "ResourceKey": "ColumnID",
    "Value": "ID"
  },
      {
    "ResourceKey": "Global_SentDate",
    "Value": "Date d'envoi"
  },
    
   ]
}
